{"cameraMode":{"drawMode":0,"name":"Shaded","section":"Shading Mode"},"sceneLighting":false,"audioPlay":false,"sceneViewState":{"m_AlwaysRefresh":false,"showFog":true,"showSkybox":false,"showFlares":true,"showImageEffects":true,"showParticleSystems":true,"showVisualEffectGraphs":true,"m_FxEnabled":true},"in2DMode":false,"pivot":{"x":-0.1653251349925995,"y":0.8489213585853577,"z":-0.7759128212928772},"rotation":{"x":0.027140581980347635,"y":-0.9562221169471741,"z":0.27580684423446658,"w":0.0941128134727478},"size":1.4664700031280518,"orthographic":false}